qoai_pennylane/__init__.py
qoai_pennylane-0.0.2.dist-info/LICENSE.txt
qoai_pennylane-0.0.2.dist-info/METADATA
qoai_pennylane-0.0.2.dist-info/WHEEL
qoai_pennylane-0.0.2.dist-info/top_level.txt
qoai_pennylane-0.0.2.dist-info/RECORD
