Metadata-Version: 2.1
Name: qoai-pennylane
Version: 0.0.2
Summary: Xanadu Quantum API and Access Provider
Author: QuantumOpenAI
Author-email: team@quantumopenai.com
Classifier: Programming Language :: Python :: 3
Classifier: License :: OSI Approved :: MIT License
Classifier: Operating System :: OS Independent
License-File: LICENSE.txt
Requires-Dist: pennylane
Requires-Dist: strawberryfields
Requires-Dist: pennylane-sf
